molib/__init__.py
molib/colors.py
molib/figures.py
molib/logging_formatter.py
molib-0.3.1.dist-info/LICENSE
molib-0.3.1.dist-info/WHEEL
molib-0.3.1.dist-info/METADATA
molib-0.3.1.dist-info/RECORD
