Metadata-Version: 2.1
Name: molib
Version: 0.3.1
Summary: Manny's code snippets
Home-page: UNKNOWN
License: MIT
Author: Manny Ochoa
Author-email: dev@manuelochoa.com
Requires-Python: >=3.6,<4.0
Classifier: License :: OSI Approved :: MIT License
Classifier: Programming Language :: Python :: 3
Classifier: Programming Language :: Python :: 3.6
Classifier: Programming Language :: Python :: 3.7
Requires-Dist: matplotlib (>=3.0,<4.0)
